print_msg.py
print_msg-0.9.4.2.dist-info/LICENSE
print_msg-0.9.4.2.dist-info/METADATA
print_msg-0.9.4.2.dist-info/WHEEL
print_msg-0.9.4.2.dist-info/top_level.txt
print_msg-0.9.4.2.dist-info/RECORD
