Metadata-Version: 2.1
Name: print-msg
Version: 0.9.4.2
Summary: Print colored status messages.
Home-page: https://github.com/shvetsovdmitry/print-msg
Author: Shvetsov Dmitry
Author-email: shvetsovdmitry1996@gmail.com
License: MIT
Project-URL: Tracker, https://github.com/shvetsovdmitry/print-msg/issues
Project-URL: Source, https://github.com/shvetsovdmitry/print-msg
Keywords: colored status messages module python
Platform: UNKNOWN
Classifier: Development Status :: 3 - Alpha
Classifier: Intended Audience :: Developers
Classifier: Programming Language :: Python :: 3
Classifier: Programming Language :: Python :: 3.4
Classifier: Programming Language :: Python :: 3.5
Classifier: Programming Language :: Python :: 3.6
Classifier: Programming Language :: Python :: 3.7
Classifier: License :: OSI Approved :: MIT License
Classifier: Operating System :: OS Independent
Classifier: Topic :: Software Development :: Libraries :: Python Modules
Requires-Python: ~=3.4
Requires-Dist: termcolor (==1.1.0) ; python_version > "3.4"
Provides-Extra: termcolor
Requires-Dist: termcolor (==1.1.0) ; extra == 'termcolor'
